hackerearth_box/exceptions.py
hackerearth_box/config_parser.py
hackerearth_box/__init__.py
hackerearth_box/install.py
hackerearth_box/utils.py
hackerearth_box-0.2.1.dist-info/WHEEL
hackerearth_box-0.2.1.dist-info/DESCRIPTION.rst
hackerearth_box-0.2.1.dist-info/METADATA
hackerearth_box-0.2.1.dist-info/RECORD
hackerearth_box-0.2.1.dist-info/metadata.json
hackerearth_box-0.2.1.dist-info/top_level.txt
