Metadata-Version: 2.0
Name: hackerearth-box
Version: 0.2.1
Summary: Python Library to facilitate automated package management on distributed servers
Home-page: UNKNOWN
Author: Dhruv Agarwal
Author-email: dhruv@hackerearth.com
License: MIT
Platform: UNKNOWN
Classifier: Development Status :: 4 - Beta
Classifier: Intended Audience :: Developers
Classifier: Topic :: Internet
Classifier: License :: OSI Approved :: MIT License
Classifier: Programming Language :: Python :: 2.6
Classifier: Programming Language :: Python :: 2.7
